Metadata-Version: 2.1
Name: outviz
Version: 2.0
Summary: An library for visualization and outlier handling
Home-page: UNKNOWN
Author: Prince Vani
Author-email: princevani79@gmail.com
License: MIT
Keywords: visualization
Platform: UNKNOWN
Classifier: Development Status :: 5 - Production/Stable
Classifier: Intended Audience :: Education
Classifier: Operating System :: Microsoft :: Windows :: Windows 10
Classifier: License :: OSI Approved :: MIT License
Classifier: Programming Language :: Python :: 3
License-File: LICENSE
